avroSchemaToCsv/__init__.py
avroSchemaToCsv/main.py
avroSchemaToCsvConvertor-0.1.3.dist-info/LICENSE
avroSchemaToCsvConvertor-0.1.3.dist-info/METADATA
avroSchemaToCsvConvertor-0.1.3.dist-info/WHEEL
avroSchemaToCsvConvertor-0.1.3.dist-info/top_level.txt
avroSchemaToCsvConvertor-0.1.3.dist-info/RECORD
