Metadata-Version: 2.1
Name: avroSchemaToCsvConvertor
Version: 0.1.3
Summary: Convert Avro schema to CSV.
Home-page: UNKNOWN
Author: Nalin Das
License: UNKNOWN
Platform: UNKNOWN
Classifier: Programming Language :: Python :: 3
Classifier: License :: OSI Approved :: MIT License
Classifier: Operating System :: OS Independent
